product2schema/__init__.py
product2schema/engine.py
product2schema/extract_metadata.py
product2schema/scrape.py
product2schema/models/__init__.py
product2schema/models/engine_models.py
product2schema/models/genai_models.py
product2schema/models/product_models.py
product2schema-1.0.4.dist-info/METADATA
product2schema-1.0.4.dist-info/WHEEL
product2schema-1.0.4.dist-info/top_level.txt
product2schema-1.0.4.dist-info/RECORD
