Metadata-Version: 2.1
Name: product2schema
Version: 1.0.4
Summary: Convert product URLs into structured product data.
Author-email: Asaniczka <asaniczka@gmail.com>
Maintainer-email: Asaniczka <asaniczka@gmail.com>
License: Apache-2.0
Project-URL: Homepage, https://github.com/asaniczka/Product2Schema
Classifier: Development Status :: 4 - Beta
Classifier: Intended Audience :: Developers
Classifier: License :: OSI Approved :: Apache Software License
Classifier: Natural Language :: English
Classifier: Programming Language :: Python :: 3.10
Requires-Python: >=3.10
Requires-Dist: chompjs >1
Requires-Dist: httpx >=0.20
Requires-Dist: pydantic >=2.2
Requires-Dist: wrapworks >=1
Requires-Dist: rich >=10
Requires-Dist: python-dotenv >=1
Requires-Dist: bs4 >=0.0.2
